wdod_client_wrapper/__init__.py
wdod_client_wrapper/wdod.py
wdod_client_wrapper/wrapper.py
wdod_client_wrapper-1.0.0.dist-info/METADATA
wdod_client_wrapper-1.0.0.dist-info/WHEEL
wdod_client_wrapper-1.0.0.dist-info/top_level.txt
wdod_client_wrapper-1.0.0.dist-info/RECORD
